esbt/__init__.py
esbt/_version.py
esbt/config_proxy.py
esbt/ctx.py
esbt/func.py
esbt/model.py
esbt/models.py
esbt/settings.py
esbt/workflow.py
esbt/workflow_ctx.py
esbt/utils/__init__.py
esbt/utils/misc.py
elice_scenario_based_tester-1.0.31.dist-info/METADATA
elice_scenario_based_tester-1.0.31.dist-info/WHEEL
elice_scenario_based_tester-1.0.31.dist-info/top_level.txt
elice_scenario_based_tester-1.0.31.dist-info/RECORD
